[
    {
        "date": "2019-11-28T00:00:00",
        "rank": "175",
        "country": "Moldova",
        "ct": "MDA",
        "points": 959,
        "previousPoints": 963,
        "flag": "https://api.fifa.com/api/v1/picture/flags-sq-4/mda",
        "delta": -4
    },
    {
        "date": "2018-09-20T00:00:00",
        "rank": "173",
        "country": "Moldova",
        "ct": "MDA",
        "points": 958,
        "previousPoints": 957,
        "flag": "https://api.fifa.com/api/v1/picture/flags-sq-4/mda",
        "delta": 1
    },
    {
        "date": "2019-04-04T00:00:00",
        "rank": "171",
        "country": "Moldova",
        "ct": "MDA",
        "points": 974,
        "previousPoints": 979,
        "flag": "https://api.fifa.com/api/v1/picture/flags-sq-4/mda",
        "delta": -5
    },
    {
        "date": "2018-12-20T00:00:00",
        "rank": "170",
        "country": "Moldova",
        "ct": "MDA",
        "points": 979,
        "previousPoints": 979,
        "flag": "https://api.fifa.com/api/v1/picture/flags-sq-4/mda",
        "delta": 0
    },
    {
        "date": "2019-09-19T00:00:00",
        "rank": "172",
        "country": "Moldova",
        "ct": "MDA",
        "points": 978,
        "previousPoints": 985,
        "flag": "https://api.fifa.com/api/v1/picture/flags-sq-4/mda",
        "delta": -7
    },
    {
        "date": "2019-07-25T00:00:00",
        "rank": "171",
        "country": "Moldova",
        "ct": "MDA",
        "points": 985,
        "previousPoints": 985,
        "flag": "https://api.fifa.com/api/v1/picture/flags-sq-4/mda",
        "delta": 0
    },
    {
        "date": "2019-10-24T00:00:00",
        "rank": "175",
        "country": "Moldova",
        "ct": "MDA",
        "points": 963,
        "previousPoints": 978,
        "flag": "https://api.fifa.com/api/v1/picture/flags-sq-4/mda",
        "delta": -15
    },
    {
        "date": "2018-03-15T00:00:00",
        "rank": "170",
        "country": "Moldova",
        "ct": "MDA",
        "points": 105,
        "previousPoints": 112,
        "flag": "https://api.fifa.com/api/v1/picture/flags-sq-4/mda",
        "delta": -7
    },
    {
        "date": "2018-10-25T00:00:00",
        "rank": "171",
        "country": "Moldova",
        "ct": "MDA",
        "points": 969,
        "previousPoints": 958,
        "flag": "https://api.fifa.com/api/v1/picture/flags-sq-4/mda",
        "delta": 11
    },
    {
        "date": "2018-08-16T00:00:00",
        "rank": "175",
        "country": "Moldova",
        "ct": "MDA",
        "points": 957,
        "previousPoints": 956,
        "flag": "https://api.fifa.com/api/v1/picture/flags-sq-4/mda",
        "delta": 1
    },
    {
        "date": "2019-02-07T00:00:00",
        "rank": "170",
        "country": "Moldova",
        "ct": "MDA",
        "points": 979,
        "previousPoints": 979,
        "flag": "https://api.fifa.com/api/v1/picture/flags-sq-4/mda",
        "delta": 0
    },
    {
        "date": "2018-07-01T00:00:00",
        "rank": "173",
        "country": "Moldova",
        "ct": "MDA",
        "points": 1000,
        "previousPoints": 998,
        "flag": "https://api.fifa.com/api/v1/picture/flags-sq-4/mda",
        "delta": 2
    },
    {
        "date": "2019-06-14T00:00:00",
        "rank": "170",
        "country": "Moldova",
        "ct": "MDA",
        "points": 985,
        "previousPoints": 974,
        "flag": "https://api.fifa.com/api/v1/picture/flags-sq-4/mda",
        "delta": 11
    },
    {
        "date": "2017-12-21T00:00:00",
        "rank": "167",
        "country": "Moldova",
        "ct": "MDA",
        "points": 111,
        "previousPoints": 111,
        "flag": "https://api.fifa.com/api/v1/picture/flags-sq-4/mda",
        "delta": 0
    },
    {
        "date": "2018-06-07T00:00:00",
        "rank": "175",
        "country": "Moldova",
        "ct": "MDA",
        "points": 88,
        "previousPoints": 98,
        "flag": "https://api.fifa.com/api/v1/picture/flags-sq-4/mda",
        "delta": -10
    },
    {
        "date": "2017-11-23T00:00:00",
        "rank": "166",
        "country": "Moldova",
        "ct": "MDA",
        "points": 111,
        "previousPoints": 112,
        "flag": "https://api.fifa.com/api/v1/picture/flags-sq-4/mda",
        "delta": -1
    },
    {
        "date": "2018-05-17T00:00:00",
        "rank": "173",
        "country": "Moldova",
        "ct": "MDA",
        "points": 98,
        "previousPoints": 98,
        "flag": "https://api.fifa.com/api/v1/picture/flags-sq-4/mda",
        "delta": 0
    },
    {
        "date": "2018-11-29T00:00:00",
        "rank": "170",
        "country": "Moldova",
        "ct": "MDA",
        "points": 979,
        "previousPoints": 969,
        "flag": "https://api.fifa.com/api/v1/picture/flags-sq-4/mda",
        "delta": 10
    },
    {
        "date": "2018-02-15T00:00:00",
        "rank": "166",
        "country": "Moldova",
        "ct": "MDA",
        "points": 112,
        "previousPoints": 112,
        "flag": "https://api.fifa.com/api/v1/picture/flags-sq-4/mda",
        "delta": 0
    },
    {
        "date": "2018-01-18T00:00:00",
        "rank": "166",
        "country": "Moldova",
        "ct": "MDA",
        "points": 112,
        "previousPoints": 111,
        "flag": "https://api.fifa.com/api/v1/picture/flags-sq-4/mda",
        "delta": 1
    },
    {
        "date": "2018-04-12T00:00:00",
        "rank": "173",
        "country": "Moldova",
        "ct": "MDA",
        "points": 98,
        "previousPoints": 105,
        "flag": "https://api.fifa.com/api/v1/picture/flags-sq-4/mda",
        "delta": -7
    },
    {
        "date": "2017-10-16T00:00:00",
        "rank": "167",
        "country": "Moldova",
        "ct": "MDA",
        "points": 112,
        "previousPoints": 148,
        "flag": "https://api.fifa.com/api/v1/picture/flags-sq-4/mda",
        "delta": -36
    },
    {
        "date": "2017-09-14T00:00:00",
        "rank": "156",
        "country": "Moldova",
        "ct": "MDA",
        "points": 148,
        "previousPoints": 154,
        "flag": "https://api.fifa.com/api/v1/picture/flags-sq-4/mda",
        "delta": -6
    },
    {
        "date": "2017-06-01T00:00:00",
        "rank": "161",
        "country": "Moldova",
        "ct": "MDA",
        "points": 135,
        "previousPoints": 142,
        "flag": "https://api.fifa.com/api/v1/picture/flags-sq-4/mda",
        "delta": -7
    },
    {
        "date": "2017-07-06T00:00:00",
        "rank": "158",
        "country": "Moldova",
        "ct": "MDA",
        "points": 154,
        "previousPoints": 135,
        "flag": "https://api.fifa.com/api/v1/picture/flags-sq-4/mda",
        "delta": 19
    },
    {
        "date": "2017-08-10T00:00:00",
        "rank": "159",
        "country": "Moldova",
        "ct": "MDA",
        "points": 154,
        "previousPoints": 154,
        "flag": "https://api.fifa.com/api/v1/picture/flags-sq-4/mda",
        "delta": 0
    },
    {
        "date": "2017-03-09T00:00:00",
        "rank": "162",
        "country": "Moldova",
        "ct": "MDA",
        "points": 139,
        "previousPoints": 145,
        "flag": "https://api.fifa.com/api/v1/picture/flags-sq-4/mda",
        "delta": -6
    },
    {
        "date": "2017-05-04T00:00:00",
        "rank": "159",
        "country": "Moldova",
        "ct": "MDA",
        "points": 142,
        "previousPoints": 142,
        "flag": "https://api.fifa.com/api/v1/picture/flags-sq-4/mda",
        "delta": 0
    },
    {
        "date": "2017-04-06T00:00:00",
        "rank": "158",
        "country": "Moldova",
        "ct": "MDA",
        "points": 142,
        "previousPoints": 139,
        "flag": "https://api.fifa.com/api/v1/picture/flags-sq-4/mda",
        "delta": 3
    },
    {
        "date": "2017-02-09T00:00:00",
        "rank": "163",
        "country": "Moldova",
        "ct": "MDA",
        "points": 145,
        "previousPoints": 138,
        "flag": "https://api.fifa.com/api/v1/picture/flags-sq-4/mda",
        "delta": 7
    },
    {
        "date": "2017-01-12T00:00:00",
        "rank": "164",
        "country": "Moldova",
        "ct": "MDA",
        "points": 138,
        "previousPoints": 138,
        "flag": "https://api.fifa.com/api/v1/picture/flags-sq-4/mda",
        "delta": 0
    },
    {
        "date": "2016-12-22T00:00:00",
        "rank": "164",
        "country": "Moldova",
        "ct": "MDA",
        "points": 138,
        "previousPoints": 138,
        "flag": "https://api.fifa.com/api/v1/picture/flags-sq-4/mda",
        "delta": 0
    },
    {
        "date": "2016-10-20T00:00:00",
        "rank": "173",
        "country": "Moldova",
        "ct": "MDA",
        "points": 119,
        "previousPoints": 154,
        "flag": "https://api.fifa.com/api/v1/picture/flags-sq-4/mda",
        "delta": -35
    },
    {
        "date": "2016-11-24T00:00:00",
        "rank": "162",
        "country": "Moldova",
        "ct": "MDA",
        "points": 138,
        "previousPoints": 119,
        "flag": "https://api.fifa.com/api/v1/picture/flags-sq-4/mda",
        "delta": 19
    },
    {
        "date": "2016-09-15T00:00:00",
        "rank": "161",
        "country": "Moldova",
        "ct": "MDA",
        "points": 154,
        "previousPoints": 151,
        "flag": "https://api.fifa.com/api/v1/picture/flags-sq-4/mda",
        "delta": 3
    },
    {
        "date": "2016-08-11T00:00:00",
        "rank": "165",
        "country": "Moldova",
        "ct": "MDA",
        "points": 151,
        "previousPoints": 151,
        "flag": "https://api.fifa.com/api/v1/picture/flags-sq-4/mda",
        "delta": 0
    },
    {
        "date": "2016-05-05T00:00:00",
        "rank": "156",
        "country": "Moldova",
        "ct": "MDA",
        "points": 181,
        "previousPoints": 181,
        "flag": "https://api.fifa.com/api/v1/picture/flags-sq-4/mda",
        "delta": 0
    },
    {
        "date": "2016-07-14T00:00:00",
        "rank": "166",
        "country": "Moldova",
        "ct": "MDA",
        "points": 151,
        "previousPoints": 165,
        "flag": "https://api.fifa.com/api/v1/picture/flags-sq-4/mda",
        "delta": -14
    },
    {
        "date": "2016-03-03T00:00:00",
        "rank": "156",
        "country": "Moldova",
        "ct": "MDA",
        "points": 165,
        "previousPoints": 170,
        "flag": "https://api.fifa.com/api/v1/picture/flags-sq-4/mda",
        "delta": -5
    },
    {
        "date": "2016-04-07T00:00:00",
        "rank": "156",
        "country": "Moldova",
        "ct": "MDA",
        "points": 181,
        "previousPoints": 165,
        "flag": "https://api.fifa.com/api/v1/picture/flags-sq-4/mda",
        "delta": 16
    },
    {
        "date": "2016-02-04T00:00:00",
        "rank": "155",
        "country": "Moldova",
        "ct": "MDA",
        "points": 170,
        "previousPoints": 172,
        "flag": "https://api.fifa.com/api/v1/picture/flags-sq-4/mda",
        "delta": -2
    },
    {
        "date": "2016-06-02T00:00:00",
        "rank": "159",
        "country": "Moldova",
        "ct": "MDA",
        "points": 165,
        "previousPoints": 181,
        "flag": "https://api.fifa.com/api/v1/picture/flags-sq-4/mda",
        "delta": -16
    },
    {
        "date": "2016-01-07T00:00:00",
        "rank": "154",
        "country": "Moldova",
        "ct": "MDA",
        "points": 172,
        "previousPoints": 172,
        "flag": "https://api.fifa.com/api/v1/picture/flags-sq-4/mda",
        "delta": 0
    },
    {
        "date": "2015-12-03T00:00:00",
        "rank": "155",
        "country": "Moldova",
        "ct": "MDA",
        "points": 172,
        "previousPoints": 177,
        "flag": "https://api.fifa.com/api/v1/picture/flags-sq-4/mda",
        "delta": -5
    },
    {
        "date": "2015-11-05T00:00:00",
        "rank": "154",
        "country": "Moldova",
        "ct": "MDA",
        "points": 177,
        "previousPoints": 239,
        "flag": "https://api.fifa.com/api/v1/picture/flags-sq-4/mda",
        "delta": -62
    },
    {
        "date": "2015-10-01T00:00:00",
        "rank": "132",
        "country": "Moldova",
        "ct": "MDA",
        "points": 239,
        "previousPoints": 245,
        "flag": "https://api.fifa.com/api/v1/picture/flags-sq-4/mda",
        "delta": -6
    },
    {
        "date": "2015-09-03T00:00:00",
        "rank": "124",
        "country": "Moldova",
        "ct": "MDA",
        "points": 245,
        "previousPoints": 236,
        "flag": "https://api.fifa.com/api/v1/picture/flags-sq-4/mda",
        "delta": 9
    },
    {
        "date": "2015-08-06T00:00:00",
        "rank": "127",
        "country": "Moldova",
        "ct": "MDA",
        "points": 236,
        "previousPoints": 236,
        "flag": "https://api.fifa.com/api/v1/picture/flags-sq-4/mda",
        "delta": 0
    },
    {
        "date": "2015-05-07T00:00:00",
        "rank": "120",
        "country": "Moldova",
        "ct": "MDA",
        "points": 245,
        "previousPoints": 245,
        "flag": "https://api.fifa.com/api/v1/picture/flags-sq-4/mda",
        "delta": 0
    },
    {
        "date": "2015-07-09T00:00:00",
        "rank": "124",
        "country": "Moldova",
        "ct": "MDA",
        "points": 236,
        "previousPoints": 219,
        "flag": "https://api.fifa.com/api/v1/picture/flags-sq-4/mda",
        "delta": 17
    },
    {
        "date": "2015-03-12T00:00:00",
        "rank": "122",
        "country": "Moldova",
        "ct": "MDA",
        "points": 243,
        "previousPoints": 254,
        "flag": "https://api.fifa.com/api/v1/picture/flags-sq-4/mda",
        "delta": -11
    },
    {
        "date": "2015-04-09T00:00:00",
        "rank": "121",
        "country": "Moldova",
        "ct": "MDA",
        "points": 245,
        "previousPoints": 243,
        "flag": "https://api.fifa.com/api/v1/picture/flags-sq-4/mda",
        "delta": 2
    },
    {
        "date": "2015-06-04T00:00:00",
        "rank": "124",
        "country": "Moldova",
        "ct": "MDA",
        "points": 219,
        "previousPoints": 245,
        "flag": "https://api.fifa.com/api/v1/picture/flags-sq-4/mda",
        "delta": -26
    },
    {
        "date": "2015-02-12T00:00:00",
        "rank": "121",
        "country": "Moldova",
        "ct": "MDA",
        "points": 254,
        "previousPoints": 250,
        "flag": "https://api.fifa.com/api/v1/picture/flags-sq-4/mda",
        "delta": 4
    },
    {
        "date": "2015-01-08T00:00:00",
        "rank": "123",
        "country": "Moldova",
        "ct": "MDA",
        "points": 250,
        "previousPoints": 250,
        "flag": "https://api.fifa.com/api/v1/picture/flags-sq-4/mda",
        "delta": 0
    },
    {
        "date": "2014-10-23T00:00:00",
        "rank": "119",
        "country": "Moldova",
        "ct": "MDA",
        "points": 262,
        "previousPoints": 302,
        "flag": "https://api.fifa.com/api/v1/picture/flags-sq-4/mda",
        "delta": -40
    },
    {
        "date": "2014-12-18T00:00:00",
        "rank": "121",
        "country": "Moldova",
        "ct": "MDA",
        "points": 250,
        "previousPoints": 250,
        "flag": "https://api.fifa.com/api/v1/picture/flags-sq-4/mda",
        "delta": 0
    },
    {
        "date": "2014-11-27T00:00:00",
        "rank": "120",
        "country": "Moldova",
        "ct": "MDA",
        "points": 250,
        "previousPoints": 262,
        "flag": "https://api.fifa.com/api/v1/picture/flags-sq-4/mda",
        "delta": -12
    },
    {
        "date": "2014-09-18T00:00:00",
        "rank": "105",
        "country": "Moldova",
        "ct": "MDA",
        "points": 302,
        "previousPoints": 325,
        "flag": "https://api.fifa.com/api/v1/picture/flags-sq-4/mda",
        "delta": -23
    },
    {
        "date": "2014-08-14T00:00:00",
        "rank": "99",
        "country": "Moldova",
        "ct": "MDA",
        "points": 325,
        "previousPoints": 325,
        "flag": "https://api.fifa.com/api/v1/picture/flags-sq-4/mda",
        "delta": 0
    },
    {
        "date": "2014-07-17T00:00:00",
        "rank": "102",
        "country": "Moldova",
        "ct": "MDA",
        "points": 325,
        "previousPoints": 334,
        "flag": "https://api.fifa.com/api/v1/picture/flags-sq-4/mda",
        "delta": -9
    },
    {
        "date": "2014-05-08T00:00:00",
        "rank": "99",
        "country": "Moldova",
        "ct": "MDA",
        "points": 325,
        "previousPoints": 325,
        "flag": "https://api.fifa.com/api/v1/picture/flags-sq-4/mda",
        "delta": 0
    },
    {
        "date": "2014-06-05T00:00:00",
        "rank": "101",
        "country": "Moldova",
        "ct": "MDA",
        "points": 334,
        "previousPoints": 325,
        "flag": "https://api.fifa.com/api/v1/picture/flags-sq-4/mda",
        "delta": 9
    },
    {
        "date": "2014-04-10T00:00:00",
        "rank": "99",
        "country": "Moldova",
        "ct": "MDA",
        "points": 325,
        "previousPoints": 303,
        "flag": "https://api.fifa.com/api/v1/picture/flags-sq-4/mda",
        "delta": 22
    },
    {
        "date": "2014-03-13T00:00:00",
        "rank": "108",
        "country": "Moldova",
        "ct": "MDA",
        "points": 303,
        "previousPoints": 305,
        "flag": "https://api.fifa.com/api/v1/picture/flags-sq-4/mda",
        "delta": -2
    },
    {
        "date": "2013-12-19T00:00:00",
        "rank": "96",
        "country": "Moldova",
        "ct": "MDA",
        "points": 359,
        "previousPoints": 359,
        "flag": "https://api.fifa.com/api/v1/picture/flags-sq-4/mda",
        "delta": 0
    },
    {
        "date": "2014-02-13T00:00:00",
        "rank": "107",
        "country": "Moldova",
        "ct": "MDA",
        "points": 305,
        "previousPoints": 359,
        "flag": "https://api.fifa.com/api/v1/picture/flags-sq-4/mda",
        "delta": -54
    },
    {
        "date": "2014-01-16T00:00:00",
        "rank": "96",
        "country": "Moldova",
        "ct": "MDA",
        "points": 359,
        "previousPoints": 359,
        "flag": "https://api.fifa.com/api/v1/picture/flags-sq-4/mda",
        "delta": 0
    },
    {
        "date": "2013-11-28T00:00:00",
        "rank": "97",
        "country": "Moldova",
        "ct": "MDA",
        "points": 359,
        "previousPoints": 369,
        "flag": "https://api.fifa.com/api/v1/picture/flags-sq-4/mda",
        "delta": -10
    },
    {
        "date": "2013-10-17T00:00:00",
        "rank": "96",
        "country": "Moldova",
        "ct": "MDA",
        "points": 369,
        "previousPoints": 237,
        "flag": "https://api.fifa.com/api/v1/picture/flags-sq-4/mda",
        "delta": 132
    },
    {
        "date": "2013-09-12T00:00:00",
        "rank": "129",
        "country": "Moldova",
        "ct": "MDA",
        "points": 237,
        "previousPoints": 256,
        "flag": "https://api.fifa.com/api/v1/picture/flags-sq-4/mda",
        "delta": -19
    },
    {
        "date": "2013-07-04T00:00:00",
        "rank": "125",
        "country": "Moldova",
        "ct": "MDA",
        "points": 256,
        "previousPoints": 230,
        "flag": "https://api.fifa.com/api/v1/picture/flags-sq-4/mda",
        "delta": 26
    },
    {
        "date": "2013-06-06T00:00:00",
        "rank": "134",
        "country": "Moldova",
        "ct": "MDA",
        "points": 230,
        "previousPoints": 214,
        "flag": "https://api.fifa.com/api/v1/picture/flags-sq-4/mda",
        "delta": 16
    },
    {
        "date": "2013-05-09T00:00:00",
        "rank": "139",
        "country": "Moldova",
        "ct": "MDA",
        "points": 214,
        "previousPoints": 214,
        "flag": "https://api.fifa.com/api/v1/picture/flags-sq-4/mda",
        "delta": 0
    },
    {
        "date": "2013-08-08T00:00:00",
        "rank": "123",
        "country": "Moldova",
        "ct": "MDA",
        "points": 256,
        "previousPoints": 256,
        "flag": "https://api.fifa.com/api/v1/picture/flags-sq-4/mda",
        "delta": 0
    },
    {
        "date": "2013-02-14T00:00:00",
        "rank": "137",
        "country": "Moldova",
        "ct": "MDA",
        "points": 228,
        "previousPoints": 255,
        "flag": "https://api.fifa.com/api/v1/picture/flags-sq-4/mda",
        "delta": -27
    },
    {
        "date": "2013-03-14T00:00:00",
        "rank": "131",
        "country": "Moldova",
        "ct": "MDA",
        "points": 232,
        "previousPoints": 228,
        "flag": "https://api.fifa.com/api/v1/picture/flags-sq-4/mda",
        "delta": 4
    },
    {
        "date": "2013-04-11T00:00:00",
        "rank": "138",
        "country": "Moldova",
        "ct": "MDA",
        "points": 214,
        "previousPoints": 232,
        "flag": "https://api.fifa.com/api/v1/picture/flags-sq-4/mda",
        "delta": -18
    },
    {
        "date": "2013-01-17T00:00:00",
        "rank": "128",
        "country": "Moldova",
        "ct": "MDA",
        "points": 255,
        "previousPoints": 255,
        "flag": "https://api.fifa.com/api/v1/picture/flags-sq-4/mda",
        "delta": 0
    },
    {
        "date": "2012-11-07T00:00:00",
        "rank": "132",
        "country": "Moldova",
        "ct": "MDA",
        "points": 241,
        "previousPoints": 187,
        "flag": "https://api.fifa.com/api/v1/picture/flags-sq-4/mda",
        "delta": 54
    },
    {
        "date": "2012-09-05T00:00:00",
        "rank": "141",
        "country": "Moldova",
        "ct": "MDA",
        "points": 204,
        "previousPoints": 213,
        "flag": "https://api.fifa.com/api/v1/picture/flags-sq-4/mda",
        "delta": -9
    },
    {
        "date": "2012-10-03T00:00:00",
        "rank": "145",
        "country": "Moldova",
        "ct": "MDA",
        "points": 187,
        "previousPoints": 204,
        "flag": "https://api.fifa.com/api/v1/picture/flags-sq-4/mda",
        "delta": -17
    },
    {
        "date": "2012-12-19T00:00:00",
        "rank": "128",
        "country": "Moldova",
        "ct": "MDA",
        "points": 255,
        "previousPoints": 241,
        "flag": "https://api.fifa.com/api/v1/picture/flags-sq-4/mda",
        "delta": 14
    },
    {
        "date": "2012-07-04T00:00:00",
        "rank": "139",
        "country": "Moldova",
        "ct": "MDA",
        "points": 213,
        "previousPoints": 212,
        "flag": "https://api.fifa.com/api/v1/picture/flags-sq-4/mda",
        "delta": 1
    },
    {
        "date": "2012-08-08T00:00:00",
        "rank": "137",
        "country": "Moldova",
        "ct": "MDA",
        "points": 213,
        "previousPoints": 213,
        "flag": "https://api.fifa.com/api/v1/picture/flags-sq-4/mda",
        "delta": 0
    },
    {
        "date": "2012-05-09T00:00:00",
        "rank": "142",
        "country": "Moldova",
        "ct": "MDA",
        "points": 222,
        "previousPoints": 222,
        "flag": "https://api.fifa.com/api/v1/picture/flags-sq-4/mda",
        "delta": 0
    },
    {
        "date": "2012-06-06T00:00:00",
        "rank": "140",
        "country": "Moldova",
        "ct": "MDA",
        "points": 212,
        "previousPoints": 222,
        "flag": "https://api.fifa.com/api/v1/picture/flags-sq-4/mda",
        "delta": -10
    },
    {
        "date": "2012-04-11T00:00:00",
        "rank": "142",
        "country": "Moldova",
        "ct": "MDA",
        "points": 222,
        "previousPoints": 216,
        "flag": "https://api.fifa.com/api/v1/picture/flags-sq-4/mda",
        "delta": 6
    },
    {
        "date": "2012-03-07T00:00:00",
        "rank": "143",
        "country": "Moldova",
        "ct": "MDA",
        "points": 216,
        "previousPoints": 205,
        "flag": "https://api.fifa.com/api/v1/picture/flags-sq-4/mda",
        "delta": 11
    },
    {
        "date": "2012-02-15T00:00:00",
        "rank": "142",
        "country": "Moldova",
        "ct": "MDA",
        "points": 205,
        "previousPoints": 229,
        "flag": "https://api.fifa.com/api/v1/picture/flags-sq-4/mda",
        "delta": -24
    },
    {
        "date": "2012-01-18T00:00:00",
        "rank": "135",
        "country": "Moldova",
        "ct": "MDA",
        "points": 229,
        "previousPoints": 229,
        "flag": "https://api.fifa.com/api/v1/picture/flags-sq-4/mda",
        "delta": 0
    },
    {
        "date": "2011-11-23T00:00:00",
        "rank": "135",
        "country": "Moldova",
        "ct": "MDA",
        "points": 229,
        "previousPoints": 255,
        "flag": "https://api.fifa.com/api/v1/picture/flags-sq-4/mda",
        "delta": -26
    },
    {
        "date": "2011-12-21T00:00:00",
        "rank": "136",
        "country": "Moldova",
        "ct": "MDA",
        "points": 229,
        "previousPoints": 229,
        "flag": "https://api.fifa.com/api/v1/picture/flags-sq-4/mda",
        "delta": 0
    },
    {
        "date": "2011-10-19T00:00:00",
        "rank": "123",
        "country": "Moldova",
        "ct": "MDA",
        "points": 255,
        "previousPoints": 255,
        "flag": "https://api.fifa.com/api/v1/picture/flags-sq-4/mda",
        "delta": 0
    },
    {
        "date": "2011-09-21T00:00:00",
        "rank": "122",
        "country": "Moldova",
        "ct": "MDA",
        "points": 255,
        "previousPoints": 364,
        "flag": "https://api.fifa.com/api/v1/picture/flags-sq-4/mda",
        "delta": -109
    },
    {
        "date": "2011-07-27T00:00:00",
        "rank": "85",
        "country": "Moldova",
        "ct": "MDA",
        "points": 383,
        "previousPoints": 383,
        "flag": "https://api.fifa.com/api/v1/picture/flags-sq-4/mda",
        "delta": 0
    },
    {
        "date": "2011-06-29T00:00:00",
        "rank": "85",
        "country": "Moldova",
        "ct": "MDA",
        "points": 383,
        "previousPoints": 394,
        "flag": "https://api.fifa.com/api/v1/picture/flags-sq-4/mda",
        "delta": -11
    },
    {
        "date": "2011-05-18T00:00:00",
        "rank": "86",
        "country": "Moldova",
        "ct": "MDA",
        "points": 394,
        "previousPoints": 394,
        "flag": "https://api.fifa.com/api/v1/picture/flags-sq-4/mda",
        "delta": 0
    },
    {
        "date": "2011-04-13T00:00:00",
        "rank": "86",
        "country": "Moldova",
        "ct": "MDA",
        "points": 394,
        "previousPoints": 383,
        "flag": "https://api.fifa.com/api/v1/picture/flags-sq-4/mda",
        "delta": 11
    },
    {
        "date": "2011-08-24T00:00:00",
        "rank": "88",
        "country": "Moldova",
        "ct": "MDA",
        "points": 364,
        "previousPoints": 383,
        "flag": "https://api.fifa.com/api/v1/picture/flags-sq-4/mda",
        "delta": -19
    },
    {
        "date": "2011-01-12T00:00:00",
        "rank": "84",
        "country": "Moldova",
        "ct": "MDA",
        "points": 411,
        "previousPoints": 411,
        "flag": "https://api.fifa.com/api/v1/picture/flags-sq-4/mda",
        "delta": 0
    },
    {
        "date": "2011-02-02T00:00:00",
        "rank": "81",
        "country": "Moldova",
        "ct": "MDA",
        "points": 411,
        "previousPoints": 411,
        "flag": "https://api.fifa.com/api/v1/picture/flags-sq-4/mda",
        "delta": 0
    },
    {
        "date": "2011-03-09T00:00:00",
        "rank": "87",
        "country": "Moldova",
        "ct": "MDA",
        "points": 383,
        "previousPoints": 411,
        "flag": "https://api.fifa.com/api/v1/picture/flags-sq-4/mda",
        "delta": -28
    },
    {
        "date": "2010-12-15T00:00:00",
        "rank": "84",
        "country": "Moldova",
        "ct": "MDA",
        "points": 411,
        "previousPoints": 405,
        "flag": "https://api.fifa.com/api/v1/picture/flags-sq-4/mda",
        "delta": 6
    },
    {
        "date": "2010-10-20T00:00:00",
        "rank": "78",
        "country": "Moldova",
        "ct": "MDA",
        "points": 424,
        "previousPoints": 398,
        "flag": "https://api.fifa.com/api/v1/picture/flags-sq-4/mda",
        "delta": 26
    },
    {
        "date": "2010-09-15T00:00:00",
        "rank": "80",
        "country": "Moldova",
        "ct": "MDA",
        "points": 398,
        "previousPoints": 350,
        "flag": "https://api.fifa.com/api/v1/picture/flags-sq-4/mda",
        "delta": 48
    },
    {
        "date": "2010-11-17T00:00:00",
        "rank": "84",
        "country": "Moldova",
        "ct": "MDA",
        "points": 405,
        "previousPoints": 424,
        "flag": "https://api.fifa.com/api/v1/picture/flags-sq-4/mda",
        "delta": -19
    },
    {
        "date": "2010-08-11T00:00:00",
        "rank": "89",
        "country": "Moldova",
        "ct": "MDA",
        "points": 350,
        "previousPoints": 350,
        "flag": "https://api.fifa.com/api/v1/picture/flags-sq-4/mda",
        "delta": 0
    },
    {
        "date": "2010-07-14T00:00:00",
        "rank": "89",
        "country": "Moldova",
        "ct": "MDA",
        "points": 350,
        "previousPoints": 378,
        "flag": "https://api.fifa.com/api/v1/picture/flags-sq-4/mda",
        "delta": -28
    },
    {
        "date": "2010-05-26T00:00:00",
        "rank": "89",
        "country": "Moldova",
        "ct": "MDA",
        "points": 378,
        "previousPoints": 392,
        "flag": "https://api.fifa.com/api/v1/picture/flags-sq-4/mda",
        "delta": -14
    },
    {
        "date": "2010-04-28T00:00:00",
        "rank": "84",
        "country": "Moldova",
        "ct": "MDA",
        "points": 392,
        "previousPoints": 373,
        "flag": "https://api.fifa.com/api/v1/picture/flags-sq-4/mda",
        "delta": 19
    },
    {
        "date": "2010-03-31T00:00:00",
        "rank": "87",
        "country": "Moldova",
        "ct": "MDA",
        "points": 373,
        "previousPoints": 328,
        "flag": "https://api.fifa.com/api/v1/picture/flags-sq-4/mda",
        "delta": 45
    },
    {
        "date": "2010-02-03T00:00:00",
        "rank": "96",
        "country": "Moldova",
        "ct": "MDA",
        "points": 338,
        "previousPoints": 338,
        "flag": "https://api.fifa.com/api/v1/picture/flags-sq-4/mda",
        "delta": 0
    },
    {
        "date": "2010-03-03T00:00:00",
        "rank": "100",
        "country": "Moldova",
        "ct": "MDA",
        "points": 328,
        "previousPoints": 338,
        "flag": "https://api.fifa.com/api/v1/picture/flags-sq-4/mda",
        "delta": -10
    },
    {
        "date": "2009-12-16T00:00:00",
        "rank": "94",
        "country": "Moldova",
        "ct": "MDA",
        "points": 338,
        "previousPoints": 338,
        "flag": "https://api.fifa.com/api/v1/picture/flags-sq-4/mda",
        "delta": 0
    },
    {
        "date": "2009-11-20T00:00:00",
        "rank": "93",
        "country": "Moldova",
        "ct": "MDA",
        "points": 338,
        "previousPoints": 371,
        "flag": "https://api.fifa.com/api/v1/picture/flags-sq-4/mda",
        "delta": -33
    },
    {
        "date": "2009-10-16T00:00:00",
        "rank": "88",
        "country": "Moldova",
        "ct": "MDA",
        "points": 371,
        "previousPoints": 390,
        "flag": "https://api.fifa.com/api/v1/picture/flags-sq-4/mda",
        "delta": -19
    },
    {
        "date": "2009-09-02T00:00:00",
        "rank": "88",
        "country": "Moldova",
        "ct": "MDA",
        "points": 390,
        "previousPoints": 389,
        "flag": "https://api.fifa.com/api/v1/picture/flags-sq-4/mda",
        "delta": 1
    },
    {
        "date": "2009-07-01T00:00:00",
        "rank": "84",
        "country": "Moldova",
        "ct": "MDA",
        "points": 389,
        "previousPoints": 338,
        "flag": "https://api.fifa.com/api/v1/picture/flags-sq-4/mda",
        "delta": 51
    },
    {
        "date": "2009-08-05T00:00:00",
        "rank": "87",
        "country": "Moldova",
        "ct": "MDA",
        "points": 389,
        "previousPoints": 389,
        "flag": "https://api.fifa.com/api/v1/picture/flags-sq-4/mda",
        "delta": 0
    },
    {
        "date": "2009-06-03T00:00:00",
        "rank": "106",
        "country": "Moldova",
        "ct": "MDA",
        "points": 338,
        "previousPoints": 387,
        "flag": "https://api.fifa.com/api/v1/picture/flags-sq-4/mda",
        "delta": -49
    },
    {
        "date": "2009-05-06T00:00:00",
        "rank": "93",
        "country": "Moldova",
        "ct": "MDA",
        "points": 387,
        "previousPoints": 387,
        "flag": "https://api.fifa.com/api/v1/picture/flags-sq-4/mda",
        "delta": 0
    },
    {
        "date": "2009-04-08T00:00:00",
        "rank": "92",
        "country": "Moldova",
        "ct": "MDA",
        "points": 387,
        "previousPoints": 362,
        "flag": "https://api.fifa.com/api/v1/picture/flags-sq-4/mda",
        "delta": 25
    },
    {
        "date": "2009-03-11T00:00:00",
        "rank": "98",
        "country": "Moldova",
        "ct": "MDA",
        "points": 362,
        "previousPoints": 362,
        "flag": "https://api.fifa.com/api/v1/picture/flags-sq-4/mda",
        "delta": 0
    },
    {
        "date": "2008-12-17T00:00:00",
        "rank": "97",
        "country": "Moldova",
        "ct": "MDA",
        "points": 373,
        "previousPoints": 449,
        "flag": "https://api.fifa.com/api/v1/picture/flags-sq-4/mda",
        "delta": -76
    },
    {
        "date": "2009-02-11T00:00:00",
        "rank": "99",
        "country": "Moldova",
        "ct": "MDA",
        "points": 362,
        "previousPoints": 373,
        "flag": "https://api.fifa.com/api/v1/picture/flags-sq-4/mda",
        "delta": -11
    },
    {
        "date": "2008-11-12T00:00:00",
        "rank": "76",
        "country": "Moldova",
        "ct": "MDA",
        "points": 449,
        "previousPoints": 500,
        "flag": "https://api.fifa.com/api/v1/picture/flags-sq-4/mda",
        "delta": -51
    },
    {
        "date": "2009-01-14T00:00:00",
        "rank": "97",
        "country": "Moldova",
        "ct": "MDA",
        "points": 373,
        "previousPoints": 373,
        "flag": "https://api.fifa.com/api/v1/picture/flags-sq-4/mda",
        "delta": 0
    },
    {
        "date": "2008-09-03T00:00:00",
        "rank": "48",
        "country": "Moldova",
        "ct": "MDA",
        "points": 573,
        "previousPoints": 622,
        "flag": "https://api.fifa.com/api/v1/picture/flags-sq-4/mda",
        "delta": -49
    },
    {
        "date": "2008-10-08T00:00:00",
        "rank": "65",
        "country": "Moldova",
        "ct": "MDA",
        "points": 500,
        "previousPoints": 573,
        "flag": "https://api.fifa.com/api/v1/picture/flags-sq-4/mda",
        "delta": -73
    },
    {
        "date": "2008-08-06T00:00:00",
        "rank": "49",
        "country": "Moldova",
        "ct": "MDA",
        "points": 622,
        "previousPoints": 622,
        "flag": "https://api.fifa.com/api/v1/picture/flags-sq-4/mda",
        "delta": 0
    },
    {
        "date": "2008-06-04T00:00:00",
        "rank": "51",
        "country": "Moldova",
        "ct": "MDA",
        "points": 583,
        "previousPoints": 670,
        "flag": "https://api.fifa.com/api/v1/picture/flags-sq-4/mda",
        "delta": -87
    },
    {
        "date": "2008-07-02T00:00:00",
        "rank": "50",
        "country": "Moldova",
        "ct": "MDA",
        "points": 622,
        "previousPoints": 583,
        "flag": "https://api.fifa.com/api/v1/picture/flags-sq-4/mda",
        "delta": 39
    },
    {
        "date": "2008-04-09T00:00:00",
        "rank": "37",
        "country": "Moldova",
        "ct": "MDA",
        "points": 669,
        "previousPoints": 594,
        "flag": "https://api.fifa.com/api/v1/picture/flags-sq-4/mda",
        "delta": 75
    },
    {
        "date": "2008-05-07T00:00:00",
        "rank": "38",
        "country": "Moldova",
        "ct": "MDA",
        "points": 670,
        "previousPoints": 669,
        "flag": "https://api.fifa.com/api/v1/picture/flags-sq-4/mda",
        "delta": 1
    },
    {
        "date": "2008-03-12T00:00:00",
        "rank": "51",
        "country": "Moldova",
        "ct": "MDA",
        "points": 594,
        "previousPoints": 602,
        "flag": "https://api.fifa.com/api/v1/picture/flags-sq-4/mda",
        "delta": -8
    },
    {
        "date": "2008-01-16T00:00:00",
        "rank": "53",
        "country": "Moldova",
        "ct": "MDA",
        "points": 579,
        "previousPoints": 579,
        "flag": "https://api.fifa.com/api/v1/picture/flags-sq-4/mda",
        "delta": 0
    },
    {
        "date": "2008-02-13T00:00:00",
        "rank": "49",
        "country": "Moldova",
        "ct": "MDA",
        "points": 602,
        "previousPoints": 579,
        "flag": "https://api.fifa.com/api/v1/picture/flags-sq-4/mda",
        "delta": 23
    },
    {
        "date": "2007-11-22T00:00:00",
        "rank": "53",
        "country": "Moldova",
        "ct": "MDA",
        "points": 579,
        "previousPoints": 497,
        "flag": "https://api.fifa.com/api/v1/picture/flags-sq-4/mda",
        "delta": 82
    },
    {
        "date": "2007-12-17T00:00:00",
        "rank": "52",
        "country": "Moldova",
        "ct": "MDA",
        "points": 579,
        "previousPoints": 579,
        "flag": "https://api.fifa.com/api/v1/picture/flags-sq-4/mda",
        "delta": 0
    },
    {
        "date": "2007-10-24T00:00:00",
        "rank": "61",
        "country": "Moldova",
        "ct": "MDA",
        "points": 497,
        "previousPoints": 413,
        "flag": "https://api.fifa.com/api/v1/picture/flags-sq-4/mda",
        "delta": 84
    },
    {
        "date": "2007-09-19T00:00:00",
        "rank": "81",
        "country": "Moldova",
        "ct": "MDA",
        "points": 413,
        "previousPoints": 292,
        "flag": "https://api.fifa.com/api/v1/picture/flags-sq-4/mda",
        "delta": 121
    },
    {
        "date": "2007-07-18T00:00:00",
        "rank": "102",
        "country": "Moldova",
        "ct": "MDA",
        "points": 320,
        "previousPoints": 320,
        "flag": "https://api.fifa.com/api/v1/picture/flags-sq-4/mda",
        "delta": 0
    },
    {
        "date": "2007-06-13T00:00:00",
        "rank": "101",
        "country": "Moldova",
        "ct": "MDA",
        "points": 320,
        "previousPoints": 344,
        "flag": "https://api.fifa.com/api/v1/picture/flags-sq-4/mda",
        "delta": -24
    },
    {
        "date": "2007-08-22T00:00:00",
        "rank": "106",
        "country": "Moldova",
        "ct": "MDA",
        "points": 292,
        "previousPoints": 320,
        "flag": "https://api.fifa.com/api/v1/picture/flags-sq-4/mda",
        "delta": -28
    },
    {
        "date": "2007-04-18T00:00:00",
        "rank": "92",
        "country": "Moldova",
        "ct": "MDA",
        "points": 345,
        "previousPoints": 342,
        "flag": "https://api.fifa.com/api/v1/picture/flags-sq-4/mda",
        "delta": 3
    },
    {
        "date": "2007-05-16T00:00:00",
        "rank": "90",
        "country": "Moldova",
        "ct": "MDA",
        "points": 344,
        "previousPoints": 345,
        "flag": "https://api.fifa.com/api/v1/picture/flags-sq-4/mda",
        "delta": -1
    },
    {
        "date": "2007-03-14T00:00:00",
        "rank": "94",
        "country": "Moldova",
        "ct": "MDA",
        "points": 342,
        "previousPoints": 373,
        "flag": "https://api.fifa.com/api/v1/picture/flags-sq-4/mda",
        "delta": -31
    },
    {
        "date": "2007-02-14T00:00:00",
        "rank": "83",
        "country": "Moldova",
        "ct": "MDA",
        "points": 373,
        "previousPoints": 382,
        "flag": "https://api.fifa.com/api/v1/picture/flags-sq-4/mda",
        "delta": -9
    },
    {
        "date": "2007-01-17T00:00:00",
        "rank": "85",
        "country": "Moldova",
        "ct": "MDA",
        "points": 382,
        "previousPoints": 382,
        "flag": "https://api.fifa.com/api/v1/picture/flags-sq-4/mda",
        "delta": 0
    },
    {
        "date": "2006-12-18T00:00:00",
        "rank": "86",
        "country": "Moldova",
        "ct": "MDA",
        "points": 382,
        "previousPoints": 382,
        "flag": "https://api.fifa.com/api/v1/picture/flags-sq-4/mda",
        "delta": 0
    },
    {
        "date": "2006-10-18T00:00:00",
        "rank": "86",
        "country": "Moldova",
        "ct": "MDA",
        "points": 382,
        "previousPoints": 356,
        "flag": "https://api.fifa.com/api/v1/picture/flags-sq-4/mda",
        "delta": 26
    },
    {
        "date": "2006-11-22T00:00:00",
        "rank": "85",
        "country": "Moldova",
        "ct": "MDA",
        "points": 382,
        "previousPoints": 382,
        "flag": "https://api.fifa.com/api/v1/picture/flags-sq-4/mda",
        "delta": 0
    },
    {
        "date": "2006-09-13T00:00:00",
        "rank": "85",
        "country": "Moldova",
        "ct": "MDA",
        "points": 356,
        "previousPoints": 416,
        "flag": "https://api.fifa.com/api/v1/picture/flags-sq-4/mda",
        "delta": -60
    },
    {
        "date": "2006-08-16T00:00:00",
        "rank": "73",
        "country": "Moldova",
        "ct": "MDA",
        "points": 416,
        "previousPoints": 416,
        "flag": "https://api.fifa.com/api/v1/picture/flags-sq-4/mda",
        "delta": 0
    },
    {
        "date": "2006-07-12T00:00:00",
        "rank": "77",
        "country": "Moldova",
        "ct": "MDA",
        "points": 416,
        "previousPoints": 452,
        "flag": "https://api.fifa.com/api/v1/picture/flags-sq-4/mda",
        "delta": -36
    },
    {
        "date": "2006-03-15T00:00:00",
        "rank": "107",
        "country": "Moldova",
        "ct": "MDA",
        "points": 437,
        "previousPoints": 440,
        "flag": "https://api.fifa.com/api/v1/picture/flags-sq-4/mda",
        "delta": -3
    },
    {
        "date": "2006-05-17T00:00:00",
        "rank": "104",
        "country": "Moldova",
        "ct": "MDA",
        "points": 452,
        "previousPoints": 453,
        "flag": "https://api.fifa.com/api/v1/picture/flags-sq-4/mda",
        "delta": -1
    },
    {
        "date": "2006-04-19T00:00:00",
        "rank": "104",
        "country": "Moldova",
        "ct": "MDA",
        "points": 453,
        "previousPoints": 437,
        "flag": "https://api.fifa.com/api/v1/picture/flags-sq-4/mda",
        "delta": 16
    },
    {
        "date": "2006-02-15T00:00:00",
        "rank": "107",
        "country": "Moldova",
        "ct": "MDA",
        "points": 440,
        "previousPoints": 441,
        "flag": "https://api.fifa.com/api/v1/picture/flags-sq-4/mda",
        "delta": -1
    },
    {
        "date": "2005-11-21T00:00:00",
        "rank": "108",
        "country": "Moldova",
        "ct": "MDA",
        "points": 441,
        "previousPoints": 441,
        "flag": "https://api.fifa.com/api/v1/picture/flags-sq-4/mda",
        "delta": 0
    },
    {
        "date": "2005-12-16T00:00:00",
        "rank": "107",
        "country": "Moldova",
        "ct": "MDA",
        "points": 442,
        "previousPoints": 441,
        "flag": "https://api.fifa.com/api/v1/picture/flags-sq-4/mda",
        "delta": 1
    },
    {
        "date": "2006-01-18T00:00:00",
        "rank": "107",
        "country": "Moldova",
        "ct": "MDA",
        "points": 441,
        "previousPoints": 442,
        "flag": "https://api.fifa.com/api/v1/picture/flags-sq-4/mda",
        "delta": -1
    },
    {
        "date": "2005-10-17T00:00:00",
        "rank": "108",
        "country": "Moldova",
        "ct": "MDA",
        "points": 441,
        "previousPoints": 436,
        "flag": "https://api.fifa.com/api/v1/picture/flags-sq-4/mda",
        "delta": 5
    },
    {
        "date": "2005-09-12T00:00:00",
        "rank": "107",
        "country": "Moldova",
        "ct": "MDA",
        "points": 436,
        "previousPoints": 414,
        "flag": "https://api.fifa.com/api/v1/picture/flags-sq-4/mda",
        "delta": 22
    },
    {
        "date": "2005-08-17T00:00:00",
        "rank": "113",
        "country": "Moldova",
        "ct": "MDA",
        "points": 414,
        "previousPoints": 416,
        "flag": "https://api.fifa.com/api/v1/picture/flags-sq-4/mda",
        "delta": -2
    },
    {
        "date": "2005-07-20T00:00:00",
        "rank": "115",
        "country": "Moldova",
        "ct": "MDA",
        "points": 416,
        "previousPoints": 418,
        "flag": "https://api.fifa.com/api/v1/picture/flags-sq-4/mda",
        "delta": -2
    },
    {
        "date": "2005-06-15T00:00:00",
        "rank": "117",
        "country": "Moldova",
        "ct": "MDA",
        "points": 418,
        "previousPoints": 423,
        "flag": "https://api.fifa.com/api/v1/picture/flags-sq-4/mda",
        "delta": -5
    },
    {
        "date": "2005-05-18T00:00:00",
        "rank": "115",
        "country": "Moldova",
        "ct": "MDA",
        "points": 423,
        "previousPoints": 431,
        "flag": "https://api.fifa.com/api/v1/picture/flags-sq-4/mda",
        "delta": -8
    },
    {
        "date": "2005-04-20T00:00:00",
        "rank": "115",
        "country": "Moldova",
        "ct": "MDA",
        "points": 431,
        "previousPoints": 433,
        "flag": "https://api.fifa.com/api/v1/picture/flags-sq-4/mda",
        "delta": -2
    },
    {
        "date": "2004-12-20T00:00:00",
        "rank": "114",
        "country": "Moldova",
        "ct": "MDA",
        "points": 429,
        "previousPoints": 434,
        "flag": "https://api.fifa.com/api/v1/picture/flags-sq-4/mda",
        "delta": -5
    },
    {
        "date": "2005-03-23T00:00:00",
        "rank": "114",
        "country": "Moldova",
        "ct": "MDA",
        "points": 433,
        "previousPoints": 431,
        "flag": "https://api.fifa.com/api/v1/picture/flags-sq-4/mda",
        "delta": 2
    },
    {
        "date": "2005-01-19T00:00:00",
        "rank": "116",
        "country": "Moldova",
        "ct": "MDA",
        "points": 428,
        "previousPoints": 429,
        "flag": "https://api.fifa.com/api/v1/picture/flags-sq-4/mda",
        "delta": -1
    },
    {
        "date": "2005-02-16T00:00:00",
        "rank": "115",
        "country": "Moldova",
        "ct": "MDA",
        "points": 431,
        "previousPoints": 428,
        "flag": "https://api.fifa.com/api/v1/picture/flags-sq-4/mda",
        "delta": 3
    },
    {
        "date": "2004-11-10T00:00:00",
        "rank": "112",
        "country": "Moldova",
        "ct": "MDA",
        "points": 434,
        "previousPoints": 425,
        "flag": "https://api.fifa.com/api/v1/picture/flags-sq-4/mda",
        "delta": 9
    },
    {
        "date": "2004-09-01T00:00:00",
        "rank": "104",
        "country": "Moldova",
        "ct": "MDA",
        "points": 438,
        "previousPoints": 424,
        "flag": "https://api.fifa.com/api/v1/picture/flags-sq-4/mda",
        "delta": 14
    },
    {
        "date": "2004-10-06T00:00:00",
        "rank": "113",
        "country": "Moldova",
        "ct": "MDA",
        "points": 425,
        "previousPoints": 438,
        "flag": "https://api.fifa.com/api/v1/picture/flags-sq-4/mda",
        "delta": -13
    },
    {
        "date": "2004-07-07T00:00:00",
        "rank": "111",
        "country": "Moldova",
        "ct": "MDA",
        "points": 426,
        "previousPoints": 425,
        "flag": "https://api.fifa.com/api/v1/picture/flags-sq-4/mda",
        "delta": 1
    },
    {
        "date": "2004-08-04T00:00:00",
        "rank": "110",
        "country": "Moldova",
        "ct": "MDA",
        "points": 424,
        "previousPoints": 426,
        "flag": "https://api.fifa.com/api/v1/picture/flags-sq-4/mda",
        "delta": -2
    },
    {
        "date": "2004-05-12T00:00:00",
        "rank": "104",
        "country": "Moldova",
        "ct": "MDA",
        "points": 438,
        "previousPoints": 432,
        "flag": "https://api.fifa.com/api/v1/picture/flags-sq-4/mda",
        "delta": 6
    },
    {
        "date": "2004-06-09T00:00:00",
        "rank": "108",
        "country": "Moldova",
        "ct": "MDA",
        "points": 425,
        "previousPoints": 438,
        "flag": "https://api.fifa.com/api/v1/picture/flags-sq-4/mda",
        "delta": -13
    },
    {
        "date": "2004-03-17T00:00:00",
        "rank": "109",
        "country": "Moldova",
        "ct": "MDA",
        "points": 429,
        "previousPoints": 432,
        "flag": "https://api.fifa.com/api/v1/picture/flags-sq-4/mda",
        "delta": -3
    },
    {
        "date": "2004-04-14T00:00:00",
        "rank": "104",
        "country": "Moldova",
        "ct": "MDA",
        "points": 432,
        "previousPoints": 429,
        "flag": "https://api.fifa.com/api/v1/picture/flags-sq-4/mda",
        "delta": 3
    },
    {
        "date": "2004-02-18T00:00:00",
        "rank": "109",
        "country": "Moldova",
        "ct": "MDA",
        "points": 432,
        "previousPoints": 433,
        "flag": "https://api.fifa.com/api/v1/picture/flags-sq-4/mda",
        "delta": -1
    },
    {
        "date": "2004-01-14T00:00:00",
        "rank": "108",
        "country": "Moldova",
        "ct": "MDA",
        "points": 433,
        "previousPoints": 434,
        "flag": "https://api.fifa.com/api/v1/picture/flags-sq-4/mda",
        "delta": -1
    },
    {
        "date": "2003-12-15T00:00:00",
        "rank": "106",
        "country": "Moldova",
        "ct": "MDA",
        "points": 434,
        "previousPoints": 429,
        "flag": "https://api.fifa.com/api/v1/picture/flags-sq-4/mda",
        "delta": 5
    },
    {
        "date": "2003-11-19T00:00:00",
        "rank": "105",
        "country": "Moldova",
        "ct": "MDA",
        "points": 429,
        "previousPoints": 430,
        "flag": "https://api.fifa.com/api/v1/picture/flags-sq-4/mda",
        "delta": -1
    },
    {
        "date": "2003-10-22T00:00:00",
        "rank": "102",
        "country": "Moldova",
        "ct": "MDA",
        "points": 430,
        "previousPoints": 431,
        "flag": "https://api.fifa.com/api/v1/picture/flags-sq-4/mda",
        "delta": -1
    },
    {
        "date": "2003-08-27T00:00:00",
        "rank": "107",
        "country": "Moldova",
        "ct": "MDA",
        "points": 409,
        "previousPoints": 409,
        "flag": "https://api.fifa.com/api/v1/picture/flags-sq-4/mda",
        "delta": 0
    },
    {
        "date": "2003-09-24T00:00:00",
        "rank": "97",
        "country": "Moldova",
        "ct": "MDA",
        "points": 431,
        "previousPoints": 409,
        "flag": "https://api.fifa.com/api/v1/picture/flags-sq-4/mda",
        "delta": 22
    },
    {
        "date": "2003-07-30T00:00:00",
        "rank": "105",
        "country": "Moldova",
        "ct": "MDA",
        "points": 409,
        "previousPoints": 412,
        "flag": "https://api.fifa.com/api/v1/picture/flags-sq-4/mda",
        "delta": -3
    },
    {
        "date": "2003-06-25T00:00:00",
        "rank": "106",
        "country": "Moldova",
        "ct": "MDA",
        "points": 412,
        "previousPoints": 392,
        "flag": "https://api.fifa.com/api/v1/picture/flags-sq-4/mda",
        "delta": 20
    },
    {
        "date": "2003-05-21T00:00:00",
        "rank": "115",
        "country": "Moldova",
        "ct": "MDA",
        "points": 392,
        "previousPoints": 395,
        "flag": "https://api.fifa.com/api/v1/picture/flags-sq-4/mda",
        "delta": -3
    },
    {
        "date": "2003-04-23T00:00:00",
        "rank": "115",
        "country": "Moldova",
        "ct": "MDA",
        "points": 395,
        "previousPoints": 388,
        "flag": "https://api.fifa.com/api/v1/picture/flags-sq-4/mda",
        "delta": 7
    },
    {
        "date": "2003-02-19T00:00:00",
        "rank": "114",
        "country": "Moldova",
        "ct": "MDA",
        "points": 384,
        "previousPoints": 386,
        "flag": "https://api.fifa.com/api/v1/picture/flags-sq-4/mda",
        "delta": -2
    },
    {
        "date": "2002-12-18T00:00:00",
        "rank": "111",
        "country": "Moldova",
        "ct": "MDA",
        "points": 386,
        "previousPoints": 384,
        "flag": "https://api.fifa.com/api/v1/picture/flags-sq-4/mda",
        "delta": 2
    },
    {
        "date": "2003-01-15T00:00:00",
        "rank": "114",
        "country": "Moldova",
        "ct": "MDA",
        "points": 386,
        "previousPoints": 386,
        "flag": "https://api.fifa.com/api/v1/picture/flags-sq-4/mda",
        "delta": 0
    },
    {
        "date": "2003-03-26T00:00:00",
        "rank": "116",
        "country": "Moldova",
        "ct": "MDA",
        "points": 388,
        "previousPoints": 384,
        "flag": "https://api.fifa.com/api/v1/picture/flags-sq-4/mda",
        "delta": 4
    },
    {
        "date": "2002-11-20T00:00:00",
        "rank": "113",
        "country": "Moldova",
        "ct": "MDA",
        "points": 384,
        "previousPoints": 391,
        "flag": "https://api.fifa.com/api/v1/picture/flags-sq-4/mda",
        "delta": -7
    },
    {
        "date": "2002-10-23T00:00:00",
        "rank": "110",
        "country": "Moldova",
        "ct": "MDA",
        "points": 391,
        "previousPoints": 398,
        "flag": "https://api.fifa.com/api/v1/picture/flags-sq-4/mda",
        "delta": -7
    },
    {
        "date": "2002-07-03T00:00:00",
        "rank": "103",
        "country": "Moldova",
        "ct": "MDA",
        "points": 415,
        "previousPoints": 425,
        "flag": "https://api.fifa.com/api/v1/picture/flags-sq-4/mda",
        "delta": -10
    },
    {
        "date": "2002-08-14T00:00:00",
        "rank": "105",
        "country": "Moldova",
        "ct": "MDA",
        "points": 405,
        "previousPoints": 415,
        "flag": "https://api.fifa.com/api/v1/picture/flags-sq-4/mda",
        "delta": -10
    },
    {
        "date": "2002-09-18T00:00:00",
        "rank": "107",
        "country": "Moldova",
        "ct": "MDA",
        "points": 398,
        "previousPoints": 405,
        "flag": "https://api.fifa.com/api/v1/picture/flags-sq-4/mda",
        "delta": -7
    },
    {
        "date": "2002-05-15T00:00:00",
        "rank": "103",
        "country": "Moldova",
        "ct": "MDA",
        "points": 425,
        "previousPoints": 430,
        "flag": "https://api.fifa.com/api/v1/picture/flags-sq-4/mda",
        "delta": -5
    },
    {
        "date": "2002-03-20T00:00:00",
        "rank": "102",
        "country": "Moldova",
        "ct": "MDA",
        "points": 439,
        "previousPoints": 435,
        "flag": "https://api.fifa.com/api/v1/picture/flags-sq-4/mda",
        "delta": 4
    },
    {
        "date": "2002-04-17T00:00:00",
        "rank": "102",
        "country": "Moldova",
        "ct": "MDA",
        "points": 430,
        "previousPoints": 439,
        "flag": "https://api.fifa.com/api/v1/picture/flags-sq-4/mda",
        "delta": -9
    },
    {
        "date": "2002-01-16T00:00:00",
        "rank": "103",
        "country": "Moldova",
        "ct": "MDA",
        "points": 437,
        "previousPoints": 437,
        "flag": "https://api.fifa.com/api/v1/picture/flags-sq-4/mda",
        "delta": 0
    },
    {
        "date": "2001-12-19T00:00:00",
        "rank": "103",
        "country": "Moldova",
        "ct": "MDA",
        "points": 437,
        "previousPoints": 437,
        "flag": "https://api.fifa.com/api/v1/picture/flags-sq-4/mda",
        "delta": 0
    },
    {
        "date": "2002-02-13T00:00:00",
        "rank": "104",
        "country": "Moldova",
        "ct": "MDA",
        "points": 435,
        "previousPoints": 437,
        "flag": "https://api.fifa.com/api/v1/picture/flags-sq-4/mda",
        "delta": -2
    },
    {
        "date": "2001-08-22T00:00:00",
        "rank": "103",
        "country": "Moldova",
        "ct": "MDA",
        "points": 422,
        "previousPoints": 422,
        "flag": "https://api.fifa.com/api/v1/picture/flags-sq-4/mda",
        "delta": 0
    },
    {
        "date": "2001-11-21T00:00:00",
        "rank": "102",
        "country": "Moldova",
        "ct": "MDA",
        "points": 437,
        "previousPoints": 437,
        "flag": "https://api.fifa.com/api/v1/picture/flags-sq-4/mda",
        "delta": 0
    },
    {
        "date": "2001-10-17T00:00:00",
        "rank": "104",
        "country": "Moldova",
        "ct": "MDA",
        "points": 437,
        "previousPoints": 440,
        "flag": "https://api.fifa.com/api/v1/picture/flags-sq-4/mda",
        "delta": -3
    },
    {
        "date": "2001-09-19T00:00:00",
        "rank": "100",
        "country": "Moldova",
        "ct": "MDA",
        "points": 440,
        "previousPoints": 422,
        "flag": "https://api.fifa.com/api/v1/picture/flags-sq-4/mda",
        "delta": 18
    },
    {
        "date": "2001-07-18T00:00:00",
        "rank": "103",
        "country": "Moldova",
        "ct": "MDA",
        "points": 422,
        "previousPoints": 424,
        "flag": "https://api.fifa.com/api/v1/picture/flags-sq-4/mda",
        "delta": -2
    },
    {
        "date": "2001-05-16T00:00:00",
        "rank": "102",
        "country": "Moldova",
        "ct": "MDA",
        "points": 421,
        "previousPoints": 424,
        "flag": "https://api.fifa.com/api/v1/picture/flags-sq-4/mda",
        "delta": -3
    },
    {
        "date": "2001-06-20T00:00:00",
        "rank": "102",
        "country": "Moldova",
        "ct": "MDA",
        "points": 424,
        "previousPoints": 421,
        "flag": "https://api.fifa.com/api/v1/picture/flags-sq-4/mda",
        "delta": 3
    },
    {
        "date": "2001-04-11T00:00:00",
        "rank": "99",
        "country": "Moldova",
        "ct": "MDA",
        "points": 424,
        "previousPoints": 426,
        "flag": "https://api.fifa.com/api/v1/picture/flags-sq-4/mda",
        "delta": -2
    },
    {
        "date": "2001-03-14T00:00:00",
        "rank": "97",
        "country": "Moldova",
        "ct": "MDA",
        "points": 426,
        "previousPoints": 429,
        "flag": "https://api.fifa.com/api/v1/picture/flags-sq-4/mda",
        "delta": -3
    },
    {
        "date": "2001-02-14T00:00:00",
        "rank": "95",
        "country": "Moldova",
        "ct": "MDA",
        "points": 429,
        "previousPoints": 430,
        "flag": "https://api.fifa.com/api/v1/picture/flags-sq-4/mda",
        "delta": -1
    },
    {
        "date": "2000-12-20T00:00:00",
        "rank": "94",
        "country": "Moldova",
        "ct": "MDA",
        "points": 430,
        "previousPoints": 426,
        "flag": "https://api.fifa.com/api/v1/picture/flags-sq-4/mda",
        "delta": 4
    },
    {
        "date": "2001-01-17T00:00:00",
        "rank": "95",
        "country": "Moldova",
        "ct": "MDA",
        "points": 430,
        "previousPoints": 430,
        "flag": "https://api.fifa.com/api/v1/picture/flags-sq-4/mda",
        "delta": 0
    },
    {
        "date": "2000-10-11T00:00:00",
        "rank": "97",
        "country": "Moldova",
        "ct": "MDA",
        "points": 417,
        "previousPoints": 423,
        "flag": "https://api.fifa.com/api/v1/picture/flags-sq-4/mda",
        "delta": -6
    },
    {
        "date": "2000-11-15T00:00:00",
        "rank": "97",
        "country": "Moldova",
        "ct": "MDA",
        "points": 426,
        "previousPoints": 417,
        "flag": "https://api.fifa.com/api/v1/picture/flags-sq-4/mda",
        "delta": 9
    },
    {
        "date": "2000-09-06T00:00:00",
        "rank": "97",
        "country": "Moldova",
        "ct": "MDA",
        "points": 423,
        "previousPoints": 415,
        "flag": "https://api.fifa.com/api/v1/picture/flags-sq-4/mda",
        "delta": 8
    },
    {
        "date": "2000-08-09T00:00:00",
        "rank": "95",
        "country": "Moldova",
        "ct": "MDA",
        "points": 415,
        "previousPoints": 415,
        "flag": "https://api.fifa.com/api/v1/picture/flags-sq-4/mda",
        "delta": 0
    },
    {
        "date": "2000-07-05T00:00:00",
        "rank": "94",
        "country": "Moldova",
        "ct": "MDA",
        "points": 415,
        "previousPoints": 421,
        "flag": "https://api.fifa.com/api/v1/picture/flags-sq-4/mda",
        "delta": -6
    },
    {
        "date": "2000-06-07T00:00:00",
        "rank": "94",
        "country": "Moldova",
        "ct": "MDA",
        "points": 421,
        "previousPoints": 422,
        "flag": "https://api.fifa.com/api/v1/picture/flags-sq-4/mda",
        "delta": -1
    },
    {
        "date": "2000-04-12T00:00:00",
        "rank": "93",
        "country": "Moldova",
        "ct": "MDA",
        "points": 413,
        "previousPoints": 414,
        "flag": "https://api.fifa.com/api/v1/picture/flags-sq-4/mda",
        "delta": -1
    },
    {
        "date": "2000-05-10T00:00:00",
        "rank": "93",
        "country": "Moldova",
        "ct": "MDA",
        "points": 422,
        "previousPoints": 413,
        "flag": "https://api.fifa.com/api/v1/picture/flags-sq-4/mda",
        "delta": 9
    },
    {
        "date": "2000-02-16T00:00:00",
        "rank": "89",
        "country": "Moldova",
        "ct": "MDA",
        "points": 419,
        "previousPoints": 398,
        "flag": "https://api.fifa.com/api/v1/picture/flags-sq-4/mda",
        "delta": 21
    },
    {
        "date": "2000-03-15T00:00:00",
        "rank": "90",
        "country": "Moldova",
        "ct": "MDA",
        "points": 414,
        "previousPoints": 419,
        "flag": "https://api.fifa.com/api/v1/picture/flags-sq-4/mda",
        "delta": -5
    },
    {
        "date": "1999-11-17T00:00:00",
        "rank": "93",
        "country": "Moldova",
        "ct": "MDA",
        "points": 401,
        "previousPoints": 401,
        "flag": "https://api.fifa.com/api/v1/picture/flags-sq-4/mda",
        "delta": 0
    },
    {
        "date": "1999-12-22T00:00:00",
        "rank": "93",
        "country": "Moldova",
        "ct": "MDA",
        "points": 398,
        "previousPoints": 401,
        "flag": "https://api.fifa.com/api/v1/picture/flags-sq-4/mda",
        "delta": -3
    },
    {
        "date": "2000-01-19T00:00:00",
        "rank": "93",
        "country": "Moldova",
        "ct": "MDA",
        "points": 398,
        "previousPoints": 398,
        "flag": "https://api.fifa.com/api/v1/picture/flags-sq-4/mda",
        "delta": 0
    },
    {
        "date": "1999-10-13T00:00:00",
        "rank": "95",
        "country": "Moldova",
        "ct": "MDA",
        "points": 401,
        "previousPoints": 398,
        "flag": "https://api.fifa.com/api/v1/picture/flags-sq-4/mda",
        "delta": 3
    },
    {
        "date": "1999-08-18T00:00:00",
        "rank": "100",
        "country": "Moldova",
        "ct": "MDA",
        "points": 372,
        "previousPoints": 372,
        "flag": "https://api.fifa.com/api/v1/picture/flags-sq-4/mda",
        "delta": 0
    },
    {
        "date": "1999-09-15T00:00:00",
        "rank": "95",
        "country": "Moldova",
        "ct": "MDA",
        "points": 398,
        "previousPoints": 372,
        "flag": "https://api.fifa.com/api/v1/picture/flags-sq-4/mda",
        "delta": 26
    },
    {
        "date": "1999-07-21T00:00:00",
        "rank": "98",
        "country": "Moldova",
        "ct": "MDA",
        "points": 372,
        "previousPoints": 372,
        "flag": "https://api.fifa.com/api/v1/picture/flags-sq-4/mda",
        "delta": 0
    },
    {
        "date": "1999-06-16T00:00:00",
        "rank": "98",
        "country": "Moldova",
        "ct": "MDA",
        "points": 372,
        "previousPoints": 360,
        "flag": "https://api.fifa.com/api/v1/picture/flags-sq-4/mda",
        "delta": 12
    },
    {
        "date": "1999-05-19T00:00:00",
        "rank": "100",
        "country": "Moldova",
        "ct": "MDA",
        "points": 360,
        "previousPoints": 361,
        "flag": "https://api.fifa.com/api/v1/picture/flags-sq-4/mda",
        "delta": -1
    },
    {
        "date": "1999-04-21T00:00:00",
        "rank": "100",
        "country": "Moldova",
        "ct": "MDA",
        "points": 361,
        "previousPoints": 353,
        "flag": "https://api.fifa.com/api/v1/picture/flags-sq-4/mda",
        "delta": 8
    },
    {
        "date": "1999-03-24T00:00:00",
        "rank": "103",
        "country": "Moldova",
        "ct": "MDA",
        "points": 353,
        "previousPoints": 340,
        "flag": "https://api.fifa.com/api/v1/picture/flags-sq-4/mda",
        "delta": 13
    },
    {
        "date": "1999-01-27T00:00:00",
        "rank": "107",
        "country": "Moldova",
        "ct": "MDA",
        "points": 341,
        "previousPoints": 25,
        "flag": "https://api.fifa.com/api/v1/picture/flags-sq-4/mda",
        "delta": 316
    },
    {
        "date": "1999-02-24T00:00:00",
        "rank": "107",
        "country": "Moldova",
        "ct": "MDA",
        "points": 340,
        "previousPoints": 341,
        "flag": "https://api.fifa.com/api/v1/picture/flags-sq-4/mda",
        "delta": -1
    },
    {
        "date": "1998-12-23T00:00:00",
        "rank": "116",
        "country": "Moldova",
        "ct": "MDA",
        "points": 25,
        "previousPoints": 24,
        "flag": "https://api.fifa.com/api/v1/picture/flags-sq-4/mda",
        "delta": 1
    },
    {
        "date": "1998-11-18T00:00:00",
        "rank": "118",
        "country": "Moldova",
        "ct": "MDA",
        "points": 24,
        "previousPoints": 24,
        "flag": "https://api.fifa.com/api/v1/picture/flags-sq-4/mda",
        "delta": 0
    },
    {
        "date": "1998-10-21T00:00:00",
        "rank": "116",
        "country": "Moldova",
        "ct": "MDA",
        "points": 24,
        "previousPoints": 22,
        "flag": "https://api.fifa.com/api/v1/picture/flags-sq-4/mda",
        "delta": 2
    },
    {
        "date": "1998-09-16T00:00:00",
        "rank": "118",
        "country": "Moldova",
        "ct": "MDA",
        "points": 22,
        "previousPoints": 16,
        "flag": "https://api.fifa.com/api/v1/picture/flags-sq-4/mda",
        "delta": 6
    },
    {
        "date": "1998-07-15T00:00:00",
        "rank": "133",
        "country": "Moldova",
        "ct": "MDA",
        "points": 16,
        "previousPoints": 16,
        "flag": "https://api.fifa.com/api/v1/picture/flags-sq-4/mda",
        "delta": 0
    },
    {
        "date": "1998-08-19T00:00:00",
        "rank": "136",
        "country": "Moldova",
        "ct": "MDA",
        "points": 16,
        "previousPoints": 16,
        "flag": "https://api.fifa.com/api/v1/picture/flags-sq-4/mda",
        "delta": 0
    },
    {
        "date": "1998-04-22T00:00:00",
        "rank": "136",
        "country": "Moldova",
        "ct": "MDA",
        "points": 16,
        "previousPoints": 17,
        "flag": "https://api.fifa.com/api/v1/picture/flags-sq-4/mda",
        "delta": -1
    },
    {
        "date": "1998-05-20T00:00:00",
        "rank": "138",
        "country": "Moldova",
        "ct": "MDA",
        "points": 16,
        "previousPoints": 16,
        "flag": "https://api.fifa.com/api/v1/picture/flags-sq-4/mda",
        "delta": 0
    },
    {
        "date": "1998-03-18T00:00:00",
        "rank": "135",
        "country": "Moldova",
        "ct": "MDA",
        "points": 17,
        "previousPoints": 18,
        "flag": "https://api.fifa.com/api/v1/picture/flags-sq-4/mda",
        "delta": -1
    },
    {
        "date": "1998-02-18T00:00:00",
        "rank": "135",
        "country": "Moldova",
        "ct": "MDA",
        "points": 18,
        "previousPoints": 18,
        "flag": "https://api.fifa.com/api/v1/picture/flags-sq-4/mda",
        "delta": 0
    },
    {
        "date": "1997-12-23T00:00:00",
        "rank": "131",
        "country": "Moldova",
        "ct": "MDA",
        "points": 18,
        "previousPoints": 18,
        "flag": "https://api.fifa.com/api/v1/picture/flags-sq-4/mda",
        "delta": 0
    },
    {
        "date": "1997-11-19T00:00:00",
        "rank": "131",
        "country": "Moldova",
        "ct": "MDA",
        "points": 18,
        "previousPoints": 20,
        "flag": "https://api.fifa.com/api/v1/picture/flags-sq-4/mda",
        "delta": -2
    },
    {
        "date": "1997-08-20T00:00:00",
        "rank": "127",
        "country": "Moldova",
        "ct": "MDA",
        "points": 20,
        "previousPoints": 20,
        "flag": "https://api.fifa.com/api/v1/picture/flags-sq-4/mda",
        "delta": 0
    },
    {
        "date": "1997-10-17T00:00:00",
        "rank": "127",
        "country": "Moldova",
        "ct": "MDA",
        "points": 20,
        "previousPoints": 20,
        "flag": "https://api.fifa.com/api/v1/picture/flags-sq-4/mda",
        "delta": 0
    },
    {
        "date": "1997-07-16T00:00:00",
        "rank": "124",
        "country": "Moldova",
        "ct": "MDA",
        "points": 20,
        "previousPoints": 20,
        "flag": "https://api.fifa.com/api/v1/picture/flags-sq-4/mda",
        "delta": 0
    },
    {
        "date": "1997-06-18T00:00:00",
        "rank": "122",
        "country": "Moldova",
        "ct": "MDA",
        "points": 20,
        "previousPoints": 21,
        "flag": "https://api.fifa.com/api/v1/picture/flags-sq-4/mda",
        "delta": -1
    },
    {
        "date": "1997-04-09T00:00:00",
        "rank": "119",
        "country": "Moldova",
        "ct": "MDA",
        "points": 22,
        "previousPoints": 21,
        "flag": "https://api.fifa.com/api/v1/picture/flags-sq-4/mda",
        "delta": 1
    },
    {
        "date": "1997-09-17T00:00:00",
        "rank": "125",
        "country": "Moldova",
        "ct": "MDA",
        "points": 20,
        "previousPoints": 20,
        "flag": "https://api.fifa.com/api/v1/picture/flags-sq-4/mda",
        "delta": 0
    },
    {
        "date": "1997-05-14T00:00:00",
        "rank": "121",
        "country": "Moldova",
        "ct": "MDA",
        "points": 21,
        "previousPoints": 22,
        "flag": "https://api.fifa.com/api/v1/picture/flags-sq-4/mda",
        "delta": -1
    },
    {
        "date": "1997-02-27T00:00:00",
        "rank": "117",
        "country": "Moldova",
        "ct": "MDA",
        "points": 21,
        "previousPoints": 21,
        "flag": "https://api.fifa.com/api/v1/picture/flags-sq-4/mda",
        "delta": 0
    },
    {
        "date": "1996-12-18T00:00:00",
        "rank": "117",
        "country": "Moldova",
        "ct": "MDA",
        "points": 21,
        "previousPoints": 21,
        "flag": "https://api.fifa.com/api/v1/picture/flags-sq-4/mda",
        "delta": 0
    },
    {
        "date": "1996-10-23T00:00:00",
        "rank": "118",
        "country": "Moldova",
        "ct": "MDA",
        "points": 20,
        "previousPoints": 19,
        "flag": "https://api.fifa.com/api/v1/picture/flags-sq-4/mda",
        "delta": 1
    },
    {
        "date": "1996-11-20T00:00:00",
        "rank": "116",
        "country": "Moldova",
        "ct": "MDA",
        "points": 21,
        "previousPoints": 20,
        "flag": "https://api.fifa.com/api/v1/picture/flags-sq-4/mda",
        "delta": 1
    },
    {
        "date": "1996-08-28T00:00:00",
        "rank": "115",
        "country": "Moldova",
        "ct": "MDA",
        "points": 19,
        "previousPoints": 19,
        "flag": "https://api.fifa.com/api/v1/picture/flags-sq-4/mda",
        "delta": 0
    },
    {
        "date": "1996-09-25T00:00:00",
        "rank": "119",
        "country": "Moldova",
        "ct": "MDA",
        "points": 19,
        "previousPoints": 19,
        "flag": "https://api.fifa.com/api/v1/picture/flags-sq-4/mda",
        "delta": 0
    },
    {
        "date": "1996-07-03T00:00:00",
        "rank": "115",
        "country": "Moldova",
        "ct": "MDA",
        "points": 19,
        "previousPoints": 18,
        "flag": "https://api.fifa.com/api/v1/picture/flags-sq-4/mda",
        "delta": 1
    },
    {
        "date": "1996-04-24T00:00:00",
        "rank": "106",
        "country": "Moldova",
        "ct": "MDA",
        "points": 19,
        "previousPoints": 17,
        "flag": "https://api.fifa.com/api/v1/picture/flags-sq-4/mda",
        "delta": 2
    },
    {
        "date": "1996-02-21T00:00:00",
        "rank": "113",
        "country": "Moldova",
        "ct": "MDA",
        "points": 17,
        "previousPoints": 17,
        "flag": "https://api.fifa.com/api/v1/picture/flags-sq-4/mda",
        "delta": 0
    },
    {
        "date": "1996-05-22T00:00:00",
        "rank": "107",
        "country": "Moldova",
        "ct": "MDA",
        "points": 18,
        "previousPoints": 19,
        "flag": "https://api.fifa.com/api/v1/picture/flags-sq-4/mda",
        "delta": -1
    },
    {
        "date": "1995-11-21T00:00:00",
        "rank": "107",
        "country": "Moldova",
        "ct": "MDA",
        "points": 17,
        "previousPoints": 15,
        "flag": "https://api.fifa.com/api/v1/picture/flags-sq-4/mda",
        "delta": 2
    },
    {
        "date": "1995-10-17T00:00:00",
        "rank": "115",
        "country": "Moldova",
        "ct": "MDA",
        "points": 15,
        "previousPoints": 6,
        "flag": "https://api.fifa.com/api/v1/picture/flags-sq-4/mda",
        "delta": 9
    },
    {
        "date": "1996-01-24T00:00:00",
        "rank": "108",
        "country": "Moldova",
        "ct": "MDA",
        "points": 17,
        "previousPoints": 17,
        "flag": "https://api.fifa.com/api/v1/picture/flags-sq-4/mda",
        "delta": 0
    },
    {
        "date": "1995-06-13T00:00:00",
        "rank": "112",
        "country": "Moldova",
        "ct": "MDA",
        "points": 14,
        "previousPoints": 14,
        "flag": "https://api.fifa.com/api/v1/picture/flags-sq-4/mda",
        "delta": 0
    },
    {
        "date": "1995-08-22T00:00:00",
        "rank": "118",
        "country": "Moldova",
        "ct": "MDA",
        "points": 14,
        "previousPoints": 14,
        "flag": "https://api.fifa.com/api/v1/picture/flags-sq-4/mda",
        "delta": 0
    },
    {
        "date": "1995-12-19T00:00:00",
        "rank": "109",
        "country": "Moldova",
        "ct": "MDA",
        "points": 17,
        "previousPoints": 17,
        "flag": "https://api.fifa.com/api/v1/picture/flags-sq-4/mda",
        "delta": 0
    },
    {
        "date": "1995-09-19T00:00:00",
        "rank": "135",
        "country": "Moldova",
        "ct": "MDA",
        "points": 6,
        "previousPoints": 14,
        "flag": "https://api.fifa.com/api/v1/picture/flags-sq-4/mda",
        "delta": -8
    },
    {
        "date": "1995-07-25T00:00:00",
        "rank": "116",
        "country": "Moldova",
        "ct": "MDA",
        "points": 14,
        "previousPoints": 14,
        "flag": "https://api.fifa.com/api/v1/picture/flags-sq-4/mda",
        "delta": 0
    },
    {
        "date": "1994-12-20T00:00:00",
        "rank": "118",
        "country": "Moldova",
        "ct": "MDA",
        "points": 12,
        "previousPoints": 12,
        "flag": "https://api.fifa.com/api/v1/picture/flags-sq-4/mda",
        "delta": 0
    },
    {
        "date": "1994-11-22T00:00:00",
        "rank": "121",
        "country": "Moldova",
        "ct": "MDA",
        "points": 12,
        "previousPoints": 10,
        "flag": "https://api.fifa.com/api/v1/picture/flags-sq-4/mda",
        "delta": 2
    },
    {
        "date": "1995-04-19T00:00:00",
        "rank": "112",
        "country": "Moldova",
        "ct": "MDA",
        "points": 14,
        "previousPoints": 14,
        "flag": "https://api.fifa.com/api/v1/picture/flags-sq-4/mda",
        "delta": 0
    },
    {
        "date": "1995-05-16T00:00:00",
        "rank": "114",
        "country": "Moldova",
        "ct": "MDA",
        "points": 14,
        "previousPoints": 14,
        "flag": "https://api.fifa.com/api/v1/picture/flags-sq-4/mda",
        "delta": 0
    },
    {
        "date": "1995-02-20T00:00:00",
        "rank": "110",
        "country": "Moldova",
        "ct": "MDA",
        "points": 14,
        "previousPoints": 12,
        "flag": "https://api.fifa.com/api/v1/picture/flags-sq-4/mda",
        "delta": 2
    },
    {
        "date": "1994-10-25T00:00:00",
        "rank": "124",
        "country": "Moldova",
        "ct": "MDA",
        "points": 10,
        "previousPoints": 6,
        "flag": "https://api.fifa.com/api/v1/picture/flags-sq-4/mda",
        "delta": 4
    },
    {
        "date": "1994-07-21T00:00:00",
        "rank": "149",
        "country": "Moldova",
        "ct": "MDA",
        "points": 3,
        "previousPoints": 3,
        "flag": "https://api.fifa.com/api/v1/picture/flags-sq-4/mda",
        "delta": 0
    },
    {
        "date": "1994-09-13T00:00:00",
        "rank": "135",
        "country": "Moldova",
        "ct": "MDA",
        "points": 6,
        "previousPoints": 3,
        "flag": "https://api.fifa.com/api/v1/picture/flags-sq-4/mda",
        "delta": 3
    },
    {
        "date": "1994-05-17T00:00:00",
        "rank": "149",
        "country": "Moldova",
        "ct": "MDA",
        "points": 3,
        "previousPoints": null,
        "flag": "https://api.fifa.com/api/v1/picture/flags-sq-4/mda"
    },
    {
        "date": "1994-06-14T00:00:00",
        "rank": "149",
        "country": "Moldova",
        "ct": "MDA",
        "points": 3,
        "previousPoints": 3,
        "flag": "https://api.fifa.com/api/v1/picture/flags-sq-4/mda",
        "delta": 0
    }
]